stroke/__init__.py
stroke/line/__init__.py
stroke/line/abstract.py
stroke/parse/__init__.py
stroke/parse/abstract.py
stroke/parse/general.py
stroke/search/__init__.py
stroke/search/abstract.py
stroke-2.3.2.dist-info/LICENCE
stroke-2.3.2.dist-info/METADATA
stroke-2.3.2.dist-info/WHEEL
stroke-2.3.2.dist-info/top_level.txt
stroke-2.3.2.dist-info/RECORD
